github_dependents_to_sqlite-0.1.1.dist-info/licenses/LICENSE
src/__init__.py
src/cli.py
src/utils.py
github_dependents_to_sqlite-0.1.1.dist-info/METADATA
github_dependents_to_sqlite-0.1.1.dist-info/WHEEL
github_dependents_to_sqlite-0.1.1.dist-info/entry_points.txt
github_dependents_to_sqlite-0.1.1.dist-info/top_level.txt
github_dependents_to_sqlite-0.1.1.dist-info/RECORD
