Metadata-Version: 2.4
Name: github-dependents-to-sqlite
Version: 0.1.1
Summary: Save GitHub package dependents data to a SQLite database by scraping the dependency graph with support for specific package selection
Author: Mingpei Cao
License-Expression: Apache-2.0
Project-URL: Homepage, https://github.com/caomingpei/github-dependents-to-sqlite
Project-URL: Repository, https://github.com/caomingpei/github-dependents-to-sqlite
Project-URL: Issues, https://github.com/caomingpei/github-dependents-to-sqlite/issues
Project-URL: Changelog, https://github.com/caomingpei/github-dependents-to-sqlite/releases
Keywords: github,sqlite,dependents,scraping,dependency-graph
Classifier: Development Status :: 4 - Beta
Classifier: Intended Audience :: Developers
Classifier: Programming Language :: Python :: 3
Classifier: Programming Language :: Python :: 3.8
Classifier: Programming Language :: Python :: 3.9
Classifier: Programming Language :: Python :: 3.10
Classifier: Programming Language :: Python :: 3.11
Classifier: Programming Language :: Python :: 3.12
Classifier: Programming Language :: Python :: 3.13
Classifier: Programming Language :: Python :: 3.14
Classifier: Programming Language :: Python :: 3 :: Only
Classifier: Topic :: Database
Classifier: Topic :: Software Development :: Libraries :: Python Modules
Classifier: Operating System :: OS Independent
Requires-Python: >=3.8
License-File: LICENSE
Requires-Dist: sqlite-utils>=2.7.2
Requires-Dist: requests>=2.20.0
Requires-Dist: beautifulsoup4>=4.8.0
Requires-Dist: click>=7.0
Requires-Dist: tqdm>=4.50.0
Provides-Extra: test
Requires-Dist: pytest>=6.0; extra == "test"
Requires-Dist: requests-mock>=1.8; extra == "test"
Provides-Extra: dev
Requires-Dist: pytest>=6.0; extra == "dev"
Requires-Dist: requests-mock>=1.8; extra == "dev"
Requires-Dist: black>=22.0; extra == "dev"
Requires-Dist: ruff>=0.1.0; extra == "dev"
Dynamic: license-file
